{
  "frame_id": "003155",
  "point_cloud_path": "/home/vipuser/\u684c\u9762/OpenPCDet/data/kitti/training/velodyne/003155.bin",
  "records": [
    {
      "layer_name": "input_voxelized",
      "layer_type": "InputSparseTensor",
      "indice_key": "",
      "spatial_shape_zyx": [
        41,
        1600,
        1408
      ],
      "feature_shape_nc": [
        15000,
        4
      ],
      "feature_channels": 4,
      "total_cells": 92364800,
      "active_voxels": 15000,
      "sparsity": 0.0001623995288248337,
      "active_ratio_vs_prev": 1.0,
      "active_ratio_vs_input": 1.0
    },
    {
      "layer_name": "conv_input.0",
      "layer_type": "SubMConv3d",
      "indice_key": "subm1",
      "spatial_shape_zyx": [
        41,
        1600,
        1408
      ],
      "feature_shape_nc": [
        15000,
        16
      ],
      "feature_channels": 16,
      "total_cells": 92364800,
      "active_voxels": 15000,
      "sparsity": 0.0001623995288248337,
      "active_ratio_vs_prev": 1.0,
      "active_ratio_vs_input": 1.0
    },
    {
      "layer_name": "conv1.0.0",
      "layer_type": "SubMConv3d",
      "indice_key": "subm1",
      "spatial_shape_zyx": [
        41,
        1600,
        1408
      ],
      "feature_shape_nc": [
        15000,
        16
      ],
      "feature_channels": 16,
      "total_cells": 92364800,
      "active_voxels": 15000,
      "sparsity": 0.0001623995288248337,
      "active_ratio_vs_prev": 1.0,
      "active_ratio_vs_input": 1.0
    },
    {
      "layer_name": "conv2.0.0",
      "layer_type": "SparseConv3d",
      "indice_key": "spconv2",
      "spatial_shape_zyx": [
        21,
        800,
        704
      ],
      "feature_shape_nc": [
        27448,
        32
      ],
      "feature_channels": 32,
      "total_cells": 11827200,
      "active_voxels": 27448,
      "sparsity": 0.0023207521645021646,
      "active_ratio_vs_prev": 1.8298666666666668,
      "active_ratio_vs_input": 1.8298666666666668
    },
    {
      "layer_name": "conv2.1.0",
      "layer_type": "SubMConv3d",
      "indice_key": "subm2",
      "spatial_shape_zyx": [
        21,
        800,
        704
      ],
      "feature_shape_nc": [
        27448,
        32
      ],
      "feature_channels": 32,
      "total_cells": 11827200,
      "active_voxels": 27448,
      "sparsity": 0.0023207521645021646,
      "active_ratio_vs_prev": 1.0,
      "active_ratio_vs_input": 1.8298666666666668
    },
    {
      "layer_name": "conv2.2.0",
      "layer_type": "SubMConv3d",
      "indice_key": "subm2",
      "spatial_shape_zyx": [
        21,
        800,
        704
      ],
      "feature_shape_nc": [
        27448,
        32
      ],
      "feature_channels": 32,
      "total_cells": 11827200,
      "active_voxels": 27448,
      "sparsity": 0.0023207521645021646,
      "active_ratio_vs_prev": 1.0,
      "active_ratio_vs_input": 1.8298666666666668
    },
    {
      "layer_name": "conv3.0.0",
      "layer_type": "SparseConv3d",
      "indice_key": "spconv3",
      "spatial_shape_zyx": [
        11,
        400,
        352
      ],
      "feature_shape_nc": [
        17544,
        64
      ],
      "feature_channels": 64,
      "total_cells": 1548800,
      "active_voxels": 17544,
      "sparsity": 0.011327479338842976,
      "active_ratio_vs_prev": 0.6391722529874672,
      "active_ratio_vs_input": 1.1696
    },
    {
      "layer_name": "conv3.1.0",
      "layer_type": "SubMConv3d",
      "indice_key": "subm3",
      "spatial_shape_zyx": [
        11,
        400,
        352
      ],
      "feature_shape_nc": [
        17544,
        64
      ],
      "feature_channels": 64,
      "total_cells": 1548800,
      "active_voxels": 17544,
      "sparsity": 0.011327479338842976,
      "active_ratio_vs_prev": 1.0,
      "active_ratio_vs_input": 1.1696
    },
    {
      "layer_name": "conv3.2.0",
      "layer_type": "SubMConv3d",
      "indice_key": "subm3",
      "spatial_shape_zyx": [
        11,
        400,
        352
      ],
      "feature_shape_nc": [
        17544,
        64
      ],
      "feature_channels": 64,
      "total_cells": 1548800,
      "active_voxels": 17544,
      "sparsity": 0.011327479338842976,
      "active_ratio_vs_prev": 1.0,
      "active_ratio_vs_input": 1.1696
    },
    {
      "layer_name": "conv4.0.0",
      "layer_type": "SparseConv3d",
      "indice_key": "spconv4",
      "spatial_shape_zyx": [
        5,
        200,
        176
      ],
      "feature_shape_nc": [
        7677,
        64
      ],
      "feature_channels": 64,
      "total_cells": 176000,
      "active_voxels": 7677,
      "sparsity": 0.04361931818181818,
      "active_ratio_vs_prev": 0.4375854993160055,
      "active_ratio_vs_input": 0.5118
    },
    {
      "layer_name": "conv4.1.0",
      "layer_type": "SubMConv3d",
      "indice_key": "subm4",
      "spatial_shape_zyx": [
        5,
        200,
        176
      ],
      "feature_shape_nc": [
        7677,
        64
      ],
      "feature_channels": 64,
      "total_cells": 176000,
      "active_voxels": 7677,
      "sparsity": 0.04361931818181818,
      "active_ratio_vs_prev": 1.0,
      "active_ratio_vs_input": 0.5118
    },
    {
      "layer_name": "conv4.2.0",
      "layer_type": "SubMConv3d",
      "indice_key": "subm4",
      "spatial_shape_zyx": [
        5,
        200,
        176
      ],
      "feature_shape_nc": [
        7677,
        64
      ],
      "feature_channels": 64,
      "total_cells": 176000,
      "active_voxels": 7677,
      "sparsity": 0.04361931818181818,
      "active_ratio_vs_prev": 1.0,
      "active_ratio_vs_input": 0.5118
    },
    {
      "layer_name": "conv_out.0",
      "layer_type": "SparseConv3d",
      "indice_key": "spconv_down2",
      "spatial_shape_zyx": [
        2,
        200,
        176
      ],
      "feature_shape_nc": [
        5472,
        128
      ],
      "feature_channels": 128,
      "total_cells": 70400,
      "active_voxels": 5472,
      "sparsity": 0.07772727272727273,
      "active_ratio_vs_prev": 0.712778429073857,
      "active_ratio_vs_input": 0.3648
    }
  ],
  "cfg": "/home/vipuser/\u684c\u9762/OpenPCDet/tools/cfgs/kitti_models/second.yaml",
  "ckpt": "/home/vipuser/\u684c\u9762/OpenPCDet/mycode/second_7862.pth",
  "device": "cuda:0",
  "seed": 0
}